README.txt
setup.py
src/collective/__init__.py
src/collective.formwidget.uberselect.egg-info/PKG-INFO
src/collective.formwidget.uberselect.egg-info/SOURCES.txt
src/collective.formwidget.uberselect.egg-info/dependency_links.txt
src/collective.formwidget.uberselect.egg-info/namespace_packages.txt
src/collective.formwidget.uberselect.egg-info/not-zip-safe
src/collective.formwidget.uberselect.egg-info/requires.txt
src/collective.formwidget.uberselect.egg-info/top_level.txt
src/collective/formwidget/__init__.py
src/collective/formwidget/uberselect/__init__.py
src/collective/formwidget/uberselect/archetypes.py
src/collective/formwidget/uberselect/wref.py