Metadata-Version: 1.0
Name: collective.formwidget.uberselect
Version: 0.1
Summary: An uberselection widget for z3c.form.
Home-page: UNKNOWN
Author: Malthe Borch
Author-email: mborch@gmail.com
License: GPL
Keywords: zope zope2 z3c.form
Platform: UNKNOWN
Classifier: Development Status :: 4 - Beta
Classifier: Environment :: Web Environment
Classifier: Framework :: Zope3
Classifier: Intended Audience :: Developers
Classifier: License :: OSI Approved :: Zope Public License
Classifier: License :: OSI Approved :: GNU Library or Lesser General Public License (LGPL)
Classifier: Programming Language :: Python
Classifier: Topic :: Software Development :: Libraries :: Python Modules
